check_pypi_name_cli/__init__.py
check_pypi_name_cli/__main__.py
check_pypi_name_cli/cli.py
check_pypi_name_cli-0.3.0.dist-info/DESCRIPTION.rst
check_pypi_name_cli-0.3.0.dist-info/METADATA
check_pypi_name_cli-0.3.0.dist-info/RECORD
check_pypi_name_cli-0.3.0.dist-info/WHEEL
check_pypi_name_cli-0.3.0.dist-info/entry_points.txt
check_pypi_name_cli-0.3.0.dist-info/metadata.json
check_pypi_name_cli-0.3.0.dist-info/top_level.txt
