Metadata-Version: 2.0
Name: check-pypi-name-cli
Version: 0.3.0
Summary: A command line tool that checks if a package name is reserved or in use on PyPI.
Home-page: https://github.com/techdragon/python-check-pypi-name-cli
Author: Samuel Bishop
Author-email: sam@psyx.co
License: BSD
Platform: UNKNOWN
Classifier: Development Status :: 5 - Production/Stable
Classifier: Intended Audience :: Developers
Classifier: License :: OSI Approved :: BSD License
Classifier: Operating System :: Unix
Classifier: Operating System :: POSIX
Classifier: Operating System :: Microsoft :: Windows
Classifier: Programming Language :: Python
Classifier: Programming Language :: Python :: 2.7
Classifier: Programming Language :: Python :: 3
Classifier: Programming Language :: Python :: 3.3
Classifier: Programming Language :: Python :: 3.4
Classifier: Programming Language :: Python :: 3.5
Classifier: Programming Language :: Python :: 3.6
Classifier: Programming Language :: Python :: Implementation :: CPython
Classifier: Programming Language :: Python :: Implementation :: PyPy
Classifier: Topic :: Utilities
Requires-Dist: check-pypi-name (>=0.3.0)
Requires-Dist: click
